setup.py
acitoolkit/__about__.py
acitoolkit/__init__.py
acitoolkit/aciConcreteLib.py
acitoolkit/aciSearch.py
acitoolkit/aciTable.py
acitoolkit/acibaseobject.py
acitoolkit/acicounters.py
acitoolkit/acifakeapic.py
acitoolkit/aciphysobject.py
acitoolkit/acisession.py
acitoolkit/acitoolkit.py
acitoolkit/acitoolkitlib.py
acitoolkit.egg-info/PKG-INFO
acitoolkit.egg-info/SOURCES.txt
acitoolkit.egg-info/dependency_links.txt
acitoolkit.egg-info/requires.txt
acitoolkit.egg-info/top_level.txt