Metadata-Version: 1.0
Name: acitoolkit
Version: 0.2
Summary: This library allows basic Cisco ACI APIC configuration.
Home-page: http://datacenter.github.io/acitoolkit/
Author: Cisco Systems, Inc.
Author-email: acitoolkit@external.cisco.com
License: Apache License, Version 2.0
Platform: UNKNOWN
